cosmic_ray_localpool/__init__.py
cosmic_ray_localpool/executor.py
cosmic_ray_localpool-1.0.4.dist-info/METADATA
cosmic_ray_localpool-1.0.4.dist-info/RECORD
cosmic_ray_localpool-1.0.4.dist-info/WHEEL
cosmic_ray_localpool-1.0.4.dist-info/entry_points.txt
cosmic_ray_localpool-1.0.4.dist-info/top_level.txt
