Metadata-Version: 2.1
Name: cosmic-ray-localpool
Version: 1.0.4
Summary: ProcessPool execution engine plugin for Cosmic Ray.
Home-page: https://gitlab.com/pv.zarubin/cosmic_ray_plugins
Author: Pavel Zarubin
License: MIT License
Platform: UNKNOWN
Requires-Python: >=3.6.0
